{
    "AdFormat": "Формат показа объявления (IMAGE, TEXT, VIDEO, SMART_MULTIPLE и т.д.)",
    "AdGroupId": "Идентификатор группы объявлений.",
    "AdGroupName": "Название группы объявлений.",
    "AdId": "Идентификатор объявления.",
    "AdNetworkType": "Тип площадки, где показано объявление (SEARCH, AD_NETWORK).",
    "Age": "Возрастная группа пользователя: AGE_0_17, AGE_18_24, AGE_25_34, AGE_35_44, AGE_45, AGE_45_54, AGE_55, UNKNOWN.",
    "AvgClickPosition": "Средняя позиция, на которой произошел клик по объявлению.",
    "AvgCpc": "Средняя стоимость клика.",
    "AvgCpm": "Средняя стоимость тысячи показов (только для медийных кампаний).",
    "AvgEffectiveBid": "Средняя ставка за клик с учетом всех корректировок.",
    "AvgImpressionFrequency": "Средняя частота показов одному пользователю (для медийных кампаний).",
    "AvgImpressionPosition": "Средняя позиция показа объявления.",
    "AvgPageviews": "Средняя глубина просмотра сайта (по данным Яндекс Метрики).",
    "AvgTrafficVolume": "Средний объем трафика с позиций, на которых были показы объявления.",
    "AvgVideoCompleteCost": "Средняя цена досмотра 100% ролика, в рублях.",
    "BounceRate": "Доля отказов в общем количестве визитов, в процентах (по данным Яндекс Метрики).",
    "Bounces": "Количество отказов (по данным Яндекс Метрики).",
    "CampaignId": "Идентификатор кампании.",
    "CampaignName": "Название кампании.",
    "CampaignUrlPath": "URL-адрес, указанный в настройках рекламной кампании.",
    "CampaignType": "Тип кампании (TEXT_CAMPAIGN, MOBILE_APP_CAMPAIGN, DYNAMIC_TEXT_CAMPAIGN и т.д.).",
    "CarrierType": "Тип связи (CELLULAR, STATIONARY, UNKNOWN).",
    "Clicks": "Количество кликов.",
    "ClickType": "Часть объявления, по которой произошёл клик (TITLE, SITELINK1-8, VCARD и т.д.).",
    "ClientLogin": "Логин главного представителя клиента.",
    "ConversionRate": "Конверсия в процентах (по данным Яндекс Метрики).",
    "Conversions": "Количество целевых визитов (конверсий).",
    "Cost": "Стоимость кликов.",
    "CostPerConversion": "Средняя стоимость целевого визита.",
    "CPV": "Средняя цена просмотра ролика, в рублях.",
    "Criteria": "Название или текст условия показа.",
    "CriteriaId": "Идентификатор условия показа.",
    "CriteriaType": "Тип условия показа (KEYWORD, AUTOTARGETING, AUDIENCE_TARGET и т.д.).",
    "Ctr": "CTR (Click-Through Rate) в процентах.",
    "Date": "Дата, за которую приведена статистика (формат YYYY-MM-DD).",
    "Device": "Тип устройства, на котором было показано объявление (DESKTOP, MOBILE, TABLET).",
    "ExternalNetworkName": "Наименование внешней сети (SSP).",
    "Gender": "Пол пользователя (GENDER_MALE, GENDER_FEMALE, UNKNOWN).",
    "GoalsRoi": "Рентабельность инвестиций в рекламу (ROI).",
    "ImpressionReach": "Охват: количество уникальных пользователей, которым был показан баннер (для медийных кампаний).",
    "Impressions": "Количество показов.",
    "IncomeGrade": "Уровень платежеспособности пользователя (VERY_HIGH, HIGH, ABOVE_AVERAGE, OTHER).",
    "LocationOfPresenceId": "Идентификатор региона местонахождения пользователя.",
    "LocationOfPresenceName": "Название региона местонахождения пользователя.",
    "MatchedKeyword": "Подобранная фраза (например, по синониму ключевой фразы).",
    "MatchType": "Тип соответствия ключевой фразе (RELATED_KEYWORD, SYNONYM, KEYWORD, NONE).",
    "MobilePlatform": "Тип операционной системы (ANDROID, IOS, OTHER, UNKNOWN).",
    "Month": "Дата начала месяца, в формате YYYY-MM-DD.",
    "Placement": "Название площадки показов.",
    "Profit": "Прибыль (Revenue - Cost).",
    "Quarter": "Дата начала квартала, в формате YYYY-MM-DD.",
    "Query": "Поисковый запрос, по которому было показано объявление.",
    "Revenue": "Доход по целям.",
    "RlAdjustmentId": "Идентификатор условия ретаргетинга.",
    "Sessions": "Количество визитов (по данным Яндекс Метрики).",
    "Slot": "Блок показа объявления (ALONE, PREMIUMBLOCK, OTHER и т.д.).",
    "TargetingCategory": "Категория таргетинга (EXACT, ALTERNATIVE, COMPETITOR и т.д.)."
}